setup.py
pyramid_oauth2/__init__.py
pyramid_oauth2/client.py
pyramid_oauth2/server.py
pyramid_oauth2.egg-info/PKG-INFO
pyramid_oauth2.egg-info/SOURCES.txt
pyramid_oauth2.egg-info/dependency_links.txt
pyramid_oauth2.egg-info/entry_points.txt
pyramid_oauth2.egg-info/not-zip-safe
pyramid_oauth2.egg-info/requires.txt
pyramid_oauth2.egg-info/top_level.txt
pyramid_oauth2/tests/__init__.py
pyramid_oauth2/tests/test_init.py