Metadata-Version: 1.0
Name: pyramid-oauth2
Version: 0.14.1
Summary: OAuth2 support for pyramid
Home-page: delicieuxgateau.ca
Author: Loïc Faure-Lacroix
Author-email: lamerstar@gmail.com
License: UNKNOWN
Keywords: oauth2 pyramid
Platform: UNKNOWN
